rsmmus/__init__.py
rsmmus/rsmmus.py
rsmmus-0.0.8.dist-info/METADATA
rsmmus-0.0.8.dist-info/WHEEL
rsmmus-0.0.8.dist-info/top_level.txt
rsmmus-0.0.8.dist-info/RECORD
