Metadata-Version: 2.1
Name: rsmmus
Version: 0.0.8
Summary: RSM MUS Sampling Tool
Home-page: https://github.com/joy-hhh/
Author: Joy
Author-email: joyhhh@outlook.kr
Classifier: Programming Language :: Python :: 3
Classifier: License :: OSI Approved :: MIT License
Classifier: Operating System :: OS Independent
Requires-Python: >=3.8
Requires-Dist: numpy
Requires-Dist: pandas
Requires-Dist: xlsxwriter
Requires-Dist: openpyxl
